{"cost": 44.147885983625386, "centers": ["PERSON", "STRUCTURE", "FARM", "NIGHT", "TREE", "WAVES", "MOUNTAIN", "HALF_CIRCLE_FRAME", "CLIFF", "GUEST"], "points": [{"clusterDistances": {"MOUNTAIN": 1.0, "GUEST": 1.0, "FARM": 1.0, "NIGHT": 1.0, "TREE": 1.0, "PERSON": 1.0, "WAVES": 1.0, "HALF_CIRCLE_FRAME": 1.0, "STRUCTURE": 1.0, "CLIFF": 1.0}, "name": "LAKES", "center": "PERSON"}, {"clusterDistances": {"MOUNTAIN": 1.0, "GUEST": 1.0, "FARM": 1.0, "NIGHT": 1.0, "TREE": 0.997229916897507, "PERSON": 0.0, "WAVES": 1.0, "HALF_CIRCLE_FRAME": 1.0, "STRUCTURE": 1.0, "CLIFF": 1.0}, "name": "PERSON", "center": "PERSON"}, {"clusterDistances": {"MOUNTAIN": 1.0, "GUEST": 1.0, "FARM": 1.0, "NIGHT": 1.0, "TREE": 0.997229916897507, "PERSON": 0.0, "WAVES": 1.0, "HALF_CIRCLE_FRAME": 1.0, "STRUCTURE": 1.0, "CLIFF": 1.0}, "name": "FIRE", "center": "PERSON"}, {"clusterDistances": {"MOUNTAIN": 1.0, "GUEST": 1.0, "FARM": 1.0, "NIGHT": 0.962962962962963, "TREE": 0.9558011049723757, "PERSON": 1.0, "WAVES": 1.0, "HALF_CIRCLE_FRAME": 1.0, "STRUCTURE": 0.8275862068965517, "CLIFF": 1.0}, "name": "BARN", "center": "STRUCTURE"}, {"clusterDistances": {"MOUNTAIN": 0.8592233009708738, "GUEST": 0.9680851063829787, "FARM": 0.9866666666666667, "NIGHT": 0.9512195121951219, "TREE": 0.7922437673130194, "PERSON": 1.0, "WAVES": 1.0, "HALF_CIRCLE_FRAME": 0.9866666666666667, "STRUCTURE": 0.7401574803149606, "CLIFF": 1.0}, "name": "SNOW", "center": "STRUCTURE"}, {"clusterDistances": {"MOUNTAIN": 1.0, "GUEST": 1.0, "FARM": 1.0, "NIGHT": 1.0, "TREE": 0.997229916897507, "PERSON": 1.0, "WAVES": 1.0, "HALF_CIRCLE_FRAME": 1.0, "STRUCTURE": 0.9882352941176471, "CLIFF": 1.0}, "name": "DOCK", "center": "STRUCTURE"}, {"clusterDistances": {"MOUNTAIN": 0.99375, "GUEST": 1.0, "FARM": 1.0, "NIGHT": 1.0, "TREE": 0.997229916897507, "PERSON": 1.0, "WAVES": 1.0, "HALF_CIRCLE_FRAME": 1.0, "STRUCTURE": 0.9882352941176471, "CLIFF": 1.0}, "name": "TRIPLE_FRAME", "center": "STRUCTURE"}, {"clusterDistances": {"MOUNTAIN": 0.855, "GUEST": 0.9775280898876404, "FARM": 0.9855072463768116, "NIGHT": 0.9473684210526316, "TREE": 0.8088642659279779, "PERSON": 1.0, "WAVES": 1.0, "HALF_CIRCLE_FRAME": 0.9855072463768116, "STRUCTURE": 0.7272727272727273, "CLIFF": 1.0}, "name": "WINTER", "center": "STRUCTURE"}, {"clusterDistances": {"MOUNTAIN": 1.0, "GUEST": 1.0, "FARM": 1.0, "NIGHT": 1.0, "TREE": 0.9806094182825484, "PERSON": 1.0, "WAVES": 1.0, "HALF_CIRCLE_FRAME": 1.0, "STRUCTURE": 0.9176470588235294, "CLIFF": 1.0}, "name": "BRIDGE", "center": "STRUCTURE"}, {"clusterDistances": {"MOUNTAIN": 1.0, "GUEST": 1.0, "FARM": 1.0, "NIGHT": 1.0, "TREE": 0.997229916897507, "PERSON": 1.0, "WAVES": 1.0, "HALF_CIRCLE_FRAME": 1.0, "STRUCTURE": 0.9882352941176471, "CLIFF": 1.0}, "name": "BUILDING", "center": "STRUCTURE"}, {"clusterDistances": {"MOUNTAIN": 0.9013452914798207, "GUEST": 0.9905660377358491, "FARM": 0.9882352941176471, "NIGHT": 0.945054945054945, "TREE": 0.7679558011049724, "PERSON": 1.0, "WAVES": 0.9915254237288136, "HALF_CIRCLE_FRAME": 1.0, "STRUCTURE": 0.0, "CLIFF": 0.9891304347826086}, "name": "STRUCTURE", "center": "STRUCTURE"}, {"clusterDistances": {"MOUNTAIN": 0.9411764705882353, "GUEST": 0.9655172413793104, "FARM": 1.0, "NIGHT": 0.9574468085106383, "TREE": 0.9098360655737705, "PERSON": 1.0, "WAVES": 0.9253731343283582, "HALF_CIRCLE_FRAME": 1.0, "STRUCTURE": 0.9017857142857143, "CLIFF": 1.0}, "name": "OVAL_FRAME", "center": "STRUCTURE"}, {"clusterDistances": {"MOUNTAIN": 1.0, "GUEST": 1.0, "FARM": 1.0, "NIGHT": 1.0, "TREE": 0.997229916897507, "PERSON": 1.0, "WAVES": 1.0, "HALF_CIRCLE_FRAME": 1.0, "STRUCTURE": 0.9882352941176471, "CLIFF": 1.0}, "name": "WINDMILL", "center": "STRUCTURE"}, {"clusterDistances": {"MOUNTAIN": 0.989010989010989, "GUEST": 1.0, "FARM": 0.9583333333333334, "NIGHT": 0.9705882352941176, "TREE": 0.9393939393939394, "PERSON": 1.0, "WAVES": 1.0, "HALF_CIRCLE_FRAME": 1.0, "STRUCTURE": 0.8404255319148937, "CLIFF": 1.0}, "name": "FENCE", "center": "STRUCTURE"}, {"clusterDistances": {"MOUNTAIN": 1.0, "GUEST": 1.0, "FARM": 1.0, "NIGHT": 1.0, "TREE": 0.997229916897507, "PERSON": 1.0, "WAVES": 1.0, "HALF_CIRCLE_FRAME": 1.0, "STRUCTURE": 0.9882352941176471, "CLIFF": 1.0}, "name": "APPLE_FRAME", "center": "STRUCTURE"}, {"clusterDistances": {"MOUNTAIN": 1.0, "GUEST": 1.0, "FARM": 1.0, "NIGHT": 1.0, "TREE": 0.9944598337950139, "PERSON": 1.0, "WAVES": 1.0, "HALF_CIRCLE_FRAME": 1.0, "STRUCTURE": 0.9764705882352941, "CLIFF": 1.0}, "name": "MILL", "center": "STRUCTURE"}, {"clusterDistances": {"MOUNTAIN": 0.8883495145631068, "GUEST": 0.9888888888888889, "FARM": 1.0, "NIGHT": 0.9473684210526316, "TREE": 0.8088642659279779, "PERSON": 1.0, "WAVES": 1.0, "HALF_CIRCLE_FRAME": 1.0, "STRUCTURE": 0.36170212765957444, "CLIFF": 0.9868421052631579}, "name": "CABIN", "center": "STRUCTURE"}, {"clusterDistances": {"MOUNTAIN": 0.9336734693877551, "GUEST": 1.0, "FARM": 1.0, "NIGHT": 1.0, "TREE": 0.8767123287671232, "PERSON": 1.0, "WAVES": 1.0, "HALF_CIRCLE_FRAME": 1.0, "STRUCTURE": 0.8035714285714286, "CLIFF": 1.0}, "name": "PATH", "center": "STRUCTURE"}, {"clusterDistances": {"MOUNTAIN": 1.0, "GUEST": 1.0, "FARM": 0.0, "NIGHT": 1.0, "TREE": 0.997229916897507, "PERSON": 1.0, "WAVES": 1.0, "HALF_CIRCLE_FRAME": 1.0, "STRUCTURE": 0.9882352941176471, "CLIFF": 1.0}, "name": "FARM", "center": "FARM"}, {"clusterDistances": {"MOUNTAIN": 0.9821428571428571, "GUEST": 1.0, "FARM": 1.0, "NIGHT": 0.0, "TREE": 0.9752066115702479, "PERSON": 1.0, "WAVES": 0.9024390243902439, "HALF_CIRCLE_FRAME": 1.0, "STRUCTURE": 0.945054945054945, "CLIFF": 0.9444444444444444}, "name": "NIGHT", "center": "NIGHT"}, {"clusterDistances": {"MOUNTAIN": 0.9937888198757764, "GUEST": 1.0, "FARM": 1.0, "NIGHT": 0.8181818181818181, "TREE": 0.9944598337950139, "PERSON": 1.0, "WAVES": 1.0, "HALF_CIRCLE_FRAME": 1.0, "STRUCTURE": 0.9883720930232558, "CLIFF": 1.0}, "name": "AURORA_BOREALIS", "center": "NIGHT"}, {"clusterDistances": {"MOUNTAIN": 0.9938271604938271, "GUEST": 1.0, "FARM": 1.0, "NIGHT": 0.7272727272727273, "TREE": 0.9916897506925207, "PERSON": 1.0, "WAVES": 0.9722222222222222, "HALF_CIRCLE_FRAME": 1.0, "STRUCTURE": 0.9767441860465116, "CLIFF": 1.0}, "name": "MOON", "center": "NIGHT"}, {"clusterDistances": {"MOUNTAIN": 0.790625, "GUEST": 0.9493670886075949, "FARM": 1.0, "NIGHT": 0.9829059829059829, "TREE": 0.37119113573407203, "PERSON": 0.9955947136563876, "WAVES": 0.9844357976653697, "HALF_CIRCLE_FRAME": 0.9955947136563876, "STRUCTURE": 0.766798418972332, "CLIFF": 0.9870689655172413}, "name": "DECIDUOUS", "center": "TREE"}, {"clusterDistances": {"MOUNTAIN": 0.5726027397260274, "GUEST": 0.9564032697547684, "FARM": 0.997229916897507, "NIGHT": 0.9752066115702479, "TREE": 0.0, "PERSON": 0.997229916897507, "WAVES": 0.9819587628865979, "HALF_CIRCLE_FRAME": 0.997229916897507, "STRUCTURE": 0.7679558011049724, "CLIFF": 0.989041095890411}, "name": "TREE", "center": "TREE"}, {"clusterDistances": {"MOUNTAIN": 0.5759312320916905, "GUEST": 0.9563953488372093, "FARM": 0.9970326409495549, "NIGHT": 0.9734513274336283, "TREE": 0.06648199445983383, "PERSON": 0.9970326409495549, "WAVES": 0.9863387978142076, "HALF_CIRCLE_FRAME": 0.9970326409495549, "STRUCTURE": 0.7873563218390804, "CLIFF": 0.9912280701754386}, "name": "TREES", "center": "TREE"}, {"clusterDistances": {"MOUNTAIN": 0.6351351351351351, "GUEST": 0.9215686274509804, "FARM": 1.0, "NIGHT": 0.9801324503311258, "TREE": 0.6077348066298343, "PERSON": 0.993006993006993, "WAVES": 1.0, "HALF_CIRCLE_FRAME": 0.993006993006993, "STRUCTURE": 0.8542713567839196, "CLIFF": 1.0}, "name": "LAKE", "center": "TREE"}, {"clusterDistances": {"MOUNTAIN": 0.9602272727272727, "GUEST": 1.0, "FARM": 1.0, "NIGHT": 1.0, "TREE": 0.9362880886426592, "PERSON": 1.0, "WAVES": 1.0, "HALF_CIRCLE_FRAME": 1.0, "STRUCTURE": 0.9514563106796117, "CLIFF": 1.0}, "name": "FOG", "center": "TREE"}, {"clusterDistances": {"MOUNTAIN": 0.9184782608695652, "GUEST": 0.9833333333333333, "FARM": 1.0, "NIGHT": 0.9795918367346939, "TREE": 0.8919667590027701, "PERSON": 1.0, "WAVES": 1.0, "HALF_CIRCLE_FRAME": 1.0, "STRUCTURE": 0.991869918699187, "CLIFF": 0.9555555555555556}, "name": "WATERFALL", "center": "TREE"}, {"clusterDistances": {"MOUNTAIN": 1.0, "GUEST": 1.0, "FARM": 1.0, "NIGHT": 1.0, "TREE": 0.997229916897507, "PERSON": 1.0, "WAVES": 1.0, "HALF_CIRCLE_FRAME": 1.0, "STRUCTURE": 1.0, "CLIFF": 1.0}, "name": "RECTANGULAR_FRAME", "center": "TREE"}, {"clusterDistances": {"MOUNTAIN": 0.9076923076923077, "GUEST": 0.9583333333333334, "FARM": 1.0, "NIGHT": 0.967741935483871, "TREE": 0.8719346049046321, "PERSON": 1.0, "WAVES": 0.9259259259259259, "HALF_CIRCLE_FRAME": 0.9811320754716981, "STRUCTURE": 0.8780487804878049, "CLIFF": 1.0}, "name": "FRAMED", "center": "TREE"}, {"clusterDistances": {"MOUNTAIN": 0.6600790513833992, "GUEST": 0.9365079365079365, "FARM": 1.0, "NIGHT": 0.972972972972973, "TREE": 0.6259541984732824, "PERSON": 1.0, "WAVES": 0.8360655737704918, "HALF_CIRCLE_FRAME": 0.994413407821229, "STRUCTURE": 0.8471615720524017, "CLIFF": 0.9668508287292817}, "name": "CLOUDS", "center": "TREE"}, {"clusterDistances": {"MOUNTAIN": 0.7932489451476793, "GUEST": 0.9863013698630136, "FARM": 1.0, "NIGHT": 0.9926470588235294, "TREE": 0.6509695290858726, "PERSON": 1.0, "WAVES": 1.0, "HALF_CIRCLE_FRAME": 1.0, "STRUCTURE": 0.9343434343434344, "CLIFF": 0.9848484848484849}, "name": "RIVER", "center": "TREE"}, {"clusterDistances": {"MOUNTAIN": 0.7520661157024793, "GUEST": 0.9685534591194969, "FARM": 1.0, "NIGHT": 0.9867549668874173, "TREE": 0.6294277929155314, "PERSON": 1.0, "WAVES": 0.9826589595375722, "HALF_CIRCLE_FRAME": 1.0, "STRUCTURE": 0.8872549019607843, "CLIFF": 0.9932885906040269}, "name": "GRASS", "center": "TREE"}, {"clusterDistances": {"MOUNTAIN": 0.4691358024691358, "GUEST": 0.9506726457399103, "FARM": 0.9952830188679245, "NIGHT": 0.9675925925925926, "TREE": 0.4127423822714681, "PERSON": 1.0, "WAVES": 0.9918032786885246, "HALF_CIRCLE_FRAME": 1.0, "STRUCTURE": 0.7975708502024291, "CLIFF": 0.995433789954338}, "name": "CONIFER", "center": "TREE"}, {"clusterDistances": {"MOUNTAIN": 0.7096774193548387, "GUEST": 0.9710144927536232, "FARM": 1.0, "NIGHT": 1.0, "TREE": 0.6675900277008311, "PERSON": 0.9916666666666667, "WAVES": 0.9934640522875817, "HALF_CIRCLE_FRAME": 1.0, "STRUCTURE": 0.9153439153439153, "CLIFF": 1.0}, "name": "BUSHES", "center": "TREE"}, {"clusterDistances": {"MOUNTAIN": 1.0, "GUEST": 1.0, "FARM": 1.0, "NIGHT": 1.0, "TREE": 0.997229916897507, "PERSON": 1.0, "WAVES": 1.0, "HALF_CIRCLE_FRAME": 1.0, "STRUCTURE": 1.0, "CLIFF": 1.0}, "name": "WINDOW_FRAME", "center": "TREE"}, {"clusterDistances": {"MOUNTAIN": 1.0, "GUEST": 1.0, "FARM": 1.0, "NIGHT": 1.0, "TREE": 1.0, "PERSON": 1.0, "WAVES": 0.9705882352941176, "HALF_CIRCLE_FRAME": 1.0, "STRUCTURE": 1.0, "CLIFF": 1.0}, "name": "FLORIDA_FRAME", "center": "WAVES"}, {"clusterDistances": {"MOUNTAIN": 0.9946236559139785, "GUEST": 1.0, "FARM": 1.0, "NIGHT": 0.972972972972973, "TREE": 0.9922077922077922, "PERSON": 1.0, "WAVES": 0.2571428571428571, "HALF_CIRCLE_FRAME": 1.0, "STRUCTURE": 1.0, "CLIFF": 0.8333333333333334}, "name": "BEACH", "center": "WAVES"}, {"clusterDistances": {"MOUNTAIN": 1.0, "GUEST": 1.0, "FARM": 1.0, "NIGHT": 1.0, "TREE": 0.9972375690607734, "PERSON": 1.0, "WAVES": 0.9714285714285714, "HALF_CIRCLE_FRAME": 1.0, "STRUCTURE": 0.9883720930232558, "CLIFF": 1.0}, "name": "BOAT", "center": "WAVES"}, {"clusterDistances": {"MOUNTAIN": 0.9948717948717949, "GUEST": 0.9642857142857143, "FARM": 1.0, "NIGHT": 0.9069767441860466, "TREE": 0.982051282051282, "PERSON": 1.0, "WAVES": 0.05555555555555558, "HALF_CIRCLE_FRAME": 1.0, "STRUCTURE": 0.9916666666666667, "CLIFF": 0.8421052631578947}, "name": "OCEAN", "center": "WAVES"}, {"clusterDistances": {"MOUNTAIN": 0.9948186528497409, "GUEST": 0.9818181818181818, "FARM": 1.0, "NIGHT": 0.9024390243902439, "TREE": 0.9819587628865979, "PERSON": 1.0, "WAVES": 0.0, "HALF_CIRCLE_FRAME": 1.0, "STRUCTURE": 0.9915254237288136, "CLIFF": 0.8333333333333334}, "name": "WAVES", "center": "WAVES"}, {"clusterDistances": {"MOUNTAIN": 0.9637305699481865, "GUEST": 0.9666666666666667, "FARM": 1.0, "NIGHT": 1.0, "TREE": 0.9132791327913279, "PERSON": 1.0, "WAVES": 0.84375, "HALF_CIRCLE_FRAME": 1.0, "STRUCTURE": 0.9495798319327731, "CLIFF": 0.9565217391304348}, "name": "SUN", "center": "WAVES"}, {"clusterDistances": {"MOUNTAIN": 1.0, "GUEST": 1.0, "FARM": 1.0, "NIGHT": 0.9473684210526316, "TREE": 0.997289972899729, "PERSON": 1.0, "WAVES": 0.7352941176470589, "HALF_CIRCLE_FRAME": 1.0, "STRUCTURE": 1.0, "CLIFF": 1.0}, "name": "PALM_TREES", "center": "WAVES"}, {"clusterDistances": {"MOUNTAIN": 0.9128440366972477, "GUEST": 1.0, "FARM": 1.0, "NIGHT": 0.9767441860465116, "TREE": 0.8412698412698413, "PERSON": 1.0, "WAVES": 0.7802197802197802, "HALF_CIRCLE_FRAME": 1.0, "STRUCTURE": 0.948051948051948, "CLIFF": 0.9240506329113924}, "name": "ROCKS", "center": "WAVES"}, {"clusterDistances": {"MOUNTAIN": 1.0, "GUEST": 1.0, "FARM": 1.0, "NIGHT": 1.0, "TREE": 1.0, "PERSON": 1.0, "WAVES": 0.9705882352941176, "HALF_CIRCLE_FRAME": 1.0, "STRUCTURE": 1.0, "CLIFF": 1.0}, "name": "SEASHELL_FRAME", "center": "WAVES"}, {"clusterDistances": {"MOUNTAIN": 0.9813664596273292, "GUEST": 1.0, "FARM": 1.0, "NIGHT": 1.0, "TREE": 1.0, "PERSON": 1.0, "WAVES": 1.0, "HALF_CIRCLE_FRAME": 1.0, "STRUCTURE": 1.0, "CLIFF": 1.0}, "name": "CACTUS", "center": "MOUNTAIN"}, {"clusterDistances": {"MOUNTAIN": 0.99375, "GUEST": 1.0, "FARM": 1.0, "NIGHT": 1.0, "TREE": 0.997229916897507, "PERSON": 1.0, "WAVES": 1.0, "HALF_CIRCLE_FRAME": 1.0, "STRUCTURE": 1.0, "CLIFF": 1.0}, "name": "HALF_OVAL_FRAME", "center": "MOUNTAIN"}, {"clusterDistances": {"MOUNTAIN": 0.99375, "GUEST": 1.0, "FARM": 1.0, "NIGHT": 1.0, "TREE": 0.997229916897507, "PERSON": 1.0, "WAVES": 1.0, "HALF_CIRCLE_FRAME": 1.0, "STRUCTURE": 1.0, "CLIFF": 1.0}, "name": "WOOD_FRAMED", "center": "MOUNTAIN"}, {"clusterDistances": {"MOUNTAIN": 0.31875, "GUEST": 0.9083333333333333, "FARM": 1.0, "NIGHT": 0.9830508474576272, "TREE": 0.7016574585635359, "PERSON": 1.0, "WAVES": 0.9929577464788732, "HALF_CIRCLE_FRAME": 1.0, "STRUCTURE": 0.9222222222222223, "CLIFF": 1.0}, "name": "SNOWY_MOUNTAIN", "center": "MOUNTAIN"}, {"clusterDistances": {"MOUNTAIN": 0.3913043478260869, "GUEST": 0.9292035398230089, "FARM": 1.0, "NIGHT": 0.9814814814814815, "TREE": 0.7292817679558011, "PERSON": 1.0, "WAVES": 1.0, "HALF_CIRCLE_FRAME": 1.0, "STRUCTURE": 0.9047619047619048, "CLIFF": 1.0}, "name": "MOUNTAINS", "center": "MOUNTAIN"}, {"clusterDistances": {"MOUNTAIN": 0.99375, "GUEST": 1.0, "FARM": 1.0, "NIGHT": 1.0, "TREE": 0.997229916897507, "PERSON": 1.0, "WAVES": 1.0, "HALF_CIRCLE_FRAME": 1.0, "STRUCTURE": 1.0, "CLIFF": 1.0}, "name": "SPLIT_FRAME", "center": "MOUNTAIN"}, {"clusterDistances": {"MOUNTAIN": 0.8941176470588236, "GUEST": 0.9361702127659575, "FARM": 1.0, "NIGHT": 1.0, "TREE": 0.9371584699453552, "PERSON": 1.0, "WAVES": 0.9491525423728814, "HALF_CIRCLE_FRAME": 1.0, "STRUCTURE": 0.9537037037037037, "CLIFF": 1.0}, "name": "CIRRUS", "center": "MOUNTAIN"}, {"clusterDistances": {"MOUNTAIN": 0.99375, "GUEST": 1.0, "FARM": 1.0, "NIGHT": 1.0, "TREE": 0.997229916897507, "PERSON": 1.0, "WAVES": 1.0, "HALF_CIRCLE_FRAME": 1.0, "STRUCTURE": 1.0, "CLIFF": 1.0}, "name": "RECTANGLE_3D_FRAME", "center": "MOUNTAIN"}, {"clusterDistances": {"MOUNTAIN": 0.99375, "GUEST": 1.0, "FARM": 1.0, "NIGHT": 1.0, "TREE": 0.997229916897507, "PERSON": 1.0, "WAVES": 1.0, "HALF_CIRCLE_FRAME": 1.0, "STRUCTURE": 1.0, "CLIFF": 1.0}, "name": "DOUBLE_OVAL_FRAME", "center": "MOUNTAIN"}, {"clusterDistances": {"MOUNTAIN": 0.0, "GUEST": 0.935672514619883, "FARM": 1.0, "NIGHT": 0.9821428571428571, "TREE": 0.5726027397260274, "PERSON": 1.0, "WAVES": 0.9948186528497409, "HALF_CIRCLE_FRAME": 1.0, "STRUCTURE": 0.9013452914798207, "CLIFF": 1.0}, "name": "MOUNTAIN", "center": "MOUNTAIN"}, {"clusterDistances": {"MOUNTAIN": 0.77, "GUEST": 0.9411764705882353, "FARM": 1.0, "NIGHT": 0.9680851063829787, "TREE": 0.8016085790884718, "PERSON": 1.0, "WAVES": 0.8349514563106796, "HALF_CIRCLE_FRAME": 0.9883720930232558, "STRUCTURE": 0.9177215189873418, "CLIFF": 0.9555555555555556}, "name": "CUMULUS", "center": "MOUNTAIN"}, {"clusterDistances": {"MOUNTAIN": 0.99375, "GUEST": 1.0, "FARM": 1.0, "NIGHT": 1.0, "TREE": 0.997229916897507, "PERSON": 1.0, "WAVES": 1.0, "HALF_CIRCLE_FRAME": 1.0, "STRUCTURE": 1.0, "CLIFF": 1.0}, "name": "TOMB_FRAME", "center": "MOUNTAIN"}, {"clusterDistances": {"MOUNTAIN": 1.0, "GUEST": 1.0, "FARM": 1.0, "NIGHT": 1.0, "TREE": 0.997229916897507, "PERSON": 1.0, "WAVES": 1.0, "HALF_CIRCLE_FRAME": 0.0, "STRUCTURE": 1.0, "CLIFF": 1.0}, "name": "HALF_CIRCLE_FRAME", "center": "HALF_CIRCLE_FRAME"}, {"clusterDistances": {"MOUNTAIN": 1.0, "GUEST": 1.0, "FARM": 1.0, "NIGHT": 0.9090909090909091, "TREE": 1.0, "PERSON": 1.0, "WAVES": 0.9705882352941176, "HALF_CIRCLE_FRAME": 1.0, "STRUCTURE": 0.9882352941176471, "CLIFF": 0.875}, "name": "LIGHTHOUSE", "center": "CLIFF"}, {"clusterDistances": {"MOUNTAIN": 1.0, "GUEST": 1.0, "FARM": 1.0, "NIGHT": 0.9444444444444444, "TREE": 0.989041095890411, "PERSON": 1.0, "WAVES": 0.8333333333333334, "HALF_CIRCLE_FRAME": 1.0, "STRUCTURE": 0.9891304347826086, "CLIFF": 0.0}, "name": "CLIFF", "center": "CLIFF"}, {"clusterDistances": {"MOUNTAIN": 1.0, "GUEST": 0.9565217391304348, "FARM": 1.0, "NIGHT": 1.0, "TREE": 0.9944598337950139, "PERSON": 1.0, "WAVES": 1.0, "HALF_CIRCLE_FRAME": 1.0, "STRUCTURE": 0.9764705882352941, "CLIFF": 1.0}, "name": "CIRCLE_FRAME", "center": "GUEST"}, {"clusterDistances": {"MOUNTAIN": 0.99375, "GUEST": 0.9545454545454546, "FARM": 1.0, "NIGHT": 1.0, "TREE": 0.997229916897507, "PERSON": 1.0, "WAVES": 1.0, "HALF_CIRCLE_FRAME": 1.0, "STRUCTURE": 1.0, "CLIFF": 1.0}, "name": "DIANE_ANDRE", "center": "GUEST"}, {"clusterDistances": {"MOUNTAIN": 1.0, "GUEST": 0.8636363636363636, "FARM": 1.0, "NIGHT": 1.0, "TREE": 1.0, "PERSON": 1.0, "WAVES": 1.0, "HALF_CIRCLE_FRAME": 1.0, "STRUCTURE": 1.0, "CLIFF": 1.0}, "name": "PORTRAIT", "center": "GUEST"}, {"clusterDistances": {"MOUNTAIN": 0.9822485207100592, "GUEST": 0.8666666666666667, "FARM": 1.0, "NIGHT": 1.0, "TREE": 0.9724517906336088, "PERSON": 1.0, "WAVES": 1.0, "HALF_CIRCLE_FRAME": 1.0, "STRUCTURE": 0.9789473684210527, "CLIFF": 1.0}, "name": "FLOWERS", "center": "GUEST"}, {"clusterDistances": {"MOUNTAIN": 0.950920245398773, "GUEST": 0.5, "FARM": 1.0, "NIGHT": 1.0, "TREE": 0.9695290858725761, "PERSON": 1.0, "WAVES": 1.0, "HALF_CIRCLE_FRAME": 1.0, "STRUCTURE": 1.0, "CLIFF": 1.0}, "name": "STEVE_ROSS", "center": "GUEST"}, {"clusterDistances": {"MOUNTAIN": 0.9770114942528736, "GUEST": 0.9189189189189189, "FARM": 1.0, "NIGHT": 1.0, "TREE": 0.9587912087912088, "PERSON": 1.0, "WAVES": 0.9387755102040817, "HALF_CIRCLE_FRAME": 1.0, "STRUCTURE": 0.9901960784313726, "CLIFF": 1.0}, "name": "HILLS", "center": "GUEST"}, {"clusterDistances": {"MOUNTAIN": 0.935672514619883, "GUEST": 0.0, "FARM": 1.0, "NIGHT": 1.0, "TREE": 0.9564032697547684, "PERSON": 1.0, "WAVES": 0.9818181818181818, "HALF_CIRCLE_FRAME": 1.0, "STRUCTURE": 0.9905660377358491, "CLIFF": 1.0}, "name": "GUEST", "center": "GUEST"}]}